pymysqll-0.1.3.dist-info/licenses/LICENSE
yourlib/__init__.py
yourlib/core.py
yourlib/pymy.py
pymysqll-0.1.3.dist-info/METADATA
pymysqll-0.1.3.dist-info/WHEEL
pymysqll-0.1.3.dist-info/top_level.txt
pymysqll-0.1.3.dist-info/RECORD
