Metadata-Version: 2.4
Name: pymysqll
Version: 0.1.3
Summary: Библиотека
Author-email: stxanskyi <tabutsalibov8@gmail.com>
Classifier: Programming Language :: Python :: 3
Classifier: License :: OSI Approved :: MIT License
Classifier: Operating System :: OS Independent
Requires-Python: >=3.8
License-File: LICENSE
Dynamic: license-file
